{"id": "root",
   "children":
[{"TabContainer":
 {
    "id": "-129253127747341573816138991276453282638"
 ,
    "callback": "ViewTabSetCurrentTab(%tabID)"
  
 ,
     "styles": [
 
 
 {
    "Primitive": {
       
       
          "current_tab": "Int%1",
       
       
          "clip_tabs": "Boolean%false"
       
    
    }  },
 
 
 {
    "FontSize": {
       
       
          "font_size": "25"
       
    
    }  },
 
 
 {
    "SizeFlags": {
       
       
          "size_flags_horizontal": "SIZE_EXPAND_FILL",
       
       
          "size_flags_vertical": "SIZE_EXPAND_FILL"
       
    
    }  },
 
 
 {
    "AnchorPreset": {
       
       
          "set_anchors_preset": "PRESET_FULL_RECT"
       
    
    }  }
 
 ]
  
     ,
    "children":
 [{"HBoxContainer":
  {
     "id": "14",
     "name": "State Machine Language",
     "children":
  [{"VBoxContainer":
   {
      "id": "135089468761702603066019430178447550259",
      "children":
   [{"Label": {
       "id": "-49763465608137492332808847179526013730",
       "text": "State Machines Demo !"
    ,
        "styles": [
    
    
    {
       "FontSize": {
          
          
             "font_size": "25"
          
       
       }  }
    
    ]
    
    }  },{"Button":
    {
       "id": "37128833038220423895044105122836873977",
       "text": "Create New Machine",
       "callback": "MachCreate(14)"
    ,
        "styles": [
    
    
    {
       "FontSize": {
          
          
             "font_size": "20"
          
       
       }  },
    
    
    {
       "Color": {
          
          
             "font_color": "DARK_SLATE_GRAY"
          
       
       }  },
    
    
    {
       "StyleBoxFlat": 
          
          
          {
             "normal": {
                
                
                   "bg_color": "HONEYDEW"
                
             
             }  }
       
         }
    
    ]
    
    }},{"Button":
    {
       "id": "115391258215155923707590523604819851538",
       "text": "Open New Tab",
       "callback": "ViewTabCreate(-99838858398014604519232368867495786333)"
    ,
        "styles": [
    
    
    {
       "FontSize": {
          
          
             "font_size": "20"
          
       
       }  },
    
    
    {
       "Color": {
          
          
             "font_color": "DARK_SLATE_GRAY"
          
       
       }  },
    
    
    {
       "StyleBoxFlat": 
          
          
          {
             "normal": {
                
                
                   "bg_color": "GHOST_WHITE"
                
             
             }  }
       
         }
    
    ]
    
    }}
   ]
   
   ,
       "styles": [
   
   
   {
      "SizeFlags": {
         
         
            "size_flags_horizontal": "SIZE_EXPAND_FILL",
         
         
            "size_flags_vertical": "SIZE_EXPAND_FILL"
         
      
      }  },
   
   
   {
      "AnchorPreset": {
         
         
            "set_anchors_preset": "PRESET_FULL_RECT"
         
      
      }  }
   
   ]
     
   }},{"VBoxContainer":
   {
      "id": "-154090120088176846567066856867306895946",
      "children":
   [{"Label": {
       "id": "169338972922138747301083742759051170419",
       "text": "Available Machines"
    ,
        "styles": [
    
    
    {
       "FontSize": {
          
          
             "font_size": "25"
          
       
       }  }
    
    ]
    
    }  },{"Label": {
       "id": "148592580383347372241872483362661417269",
       "text": "6"
    ,
        "styles": [
    
    
    {
       "FontSize": {
          
          
             "font_size": "20"
          
       
       }  }
    
    ]
    
    }  }
   ]
   
   ,
       "styles": [
   
   
   {
      "SizeFlags": {
         
         
            "size_flags_horizontal": "SIZE_EXPAND_FILL",
         
         
            "size_flags_vertical": "SIZE_EXPAND_FILL"
         
      
      }  },
   
   
   {
      "AnchorPreset": {
         
         
            "set_anchors_preset": "PRESET_FULL_RECT"
         
      
      }  }
   
   ]
     
   }}
  ]
  
  ,
      "styles": [
  
  
  {
     "SizeFlags": {
        
        
           "size_flags_horizontal": "SIZE_EXPAND_FILL",
        
        
           "size_flags_vertical": "SIZE_EXPAND_FILL"
        
     
     }  },
  
  
  {
     "AnchorPreset": {
        
        
           "set_anchors_preset": "PRESET_FULL_RECT"
        
     
     }  }
  
  ]
   
  }}
 ]
  
 }}
]
}