{"id": "root",
   "children":
[{"TabContainer":
 {
    "id": "-169747414230117038224204866283481845054"
  
 ,
     "styles": [
 
 
 {
    "Primitive": {
       
       
          "current_tab": "Int%0",
       
       
          "clip_tabs": "Boolean%false"
       
    
    }  },
 
 
 {
    "FontSize": {
       
       
          "font_size": "20"
       
    
    }  },
 
 
 {
    "SizeFlags": {
       
       
          "size_flags_horizontal": "SIZE_EXPAND_FILL",
       
       
          "size_flags_vertical": "SIZE_EXPAND_FILL"
       
    
    }  },
 
 
 {
    "AnchorPreset": {
       
       
          "set_anchors_preset": "PRESET_FULL_RECT"
       
    
    }  }
 
 ]
  
     ,
    "children":
 [{"HBoxContainer":
  {
     "id": "11",
     "name": "State Machine Language",
     "children":
  [{"VBoxContainer":
   {
      "id": "-139101527836920223016883401141733895010",
      "children":
   [{"Label": {
       "id": "-86745483132542362696307658181396215496",
       "text": "State Machines Everywhere!"
    ,
        "styles": [
    
    
    {
       "Primary": {
          
          
             "horizontal_alignment": "Long%1"
          
       
       }  }
    
    ]
    
    }  },{"Button":
    {
       "id": "163057704199142717326771319917971826844",
       "text": "Create New Machine",
       "callback": "MachCreate(11)"
    ,
        "styles": [
    
    
    {
       "FontSize": {
          
          
             "font_size": "20"
          
       
       }  },
    
    
    {
       "Color": {
          
          
             "font_color": "DARK_SLATE_GRAY"
          
       
       }  },
    
    
    {
       "StyleBoxFlat": 
          
          
          {
             "normal": {
                
                
                   "bg_color": "HONEYDEW"
                
             
             }  }
       
         }
    
    ]
    
    }},{"Button":
    {
       "id": "-37264198839337155173013628094704120060",
       "text": "Open New Tab",
       "callback": "ViewTabCreate(-129190753892488039787251269140924297026)"
    ,
        "styles": [
    
    
    {
       "FontSize": {
          
          
             "font_size": "20"
          
       
       }  },
    
    
    {
       "StyleBoxFlat": 
          
          
          {
             "normal": {
                
                
                   "bg_color": "HONEYDEW"
                
             
             }  }
       
         }
    
    ]
    
    }}
   ]
   
   ,
       "styles": [
   
   
   {
      "SizeFlags": {
         
         
            "size_flags_horizontal": "SIZE_EXPAND_FILL",
         
         
            "size_flags_vertical": "SIZE_EXPAND_FILL"
         
      
      }  },
   
   
   {
      "AnchorPreset": {
         
         
            "set_anchors_preset": "PRESET_FULL_RECT"
         
      
      }  }
   
   ]
     
   }},{"VBoxContainer":
   {
      "id": "-72739402475314355428141110140503240822",
      "children":
   [{"Label": {
       "id": "-41001693750559784701689749896034559528",
       "text": "Available Machines"
    ,
        "styles": [
    
    
    {
       "Primary": {
          
          
             "horizontal_alignment": "1"
          
       
       }  }
    
    ]
    
    }  },{"Label": {
       "id": "-11417968578735591165533911278423228912",
       "text": "6"
    ,
        "styles": [
    
    
    {
       "FontSize": {
          
          
             "font_size": "20"
          
       
       }  }
    
    ]
    
    }  }
   ]
   
   ,
       "styles": [
   
   
   {
      "SizeFlags": {
         
         
            "size_flags_horizontal": "SIZE_EXPAND_FILL",
         
         
            "size_flags_vertical": "SIZE_EXPAND_FILL"
         
      
      }  },
   
   
   {
      "AnchorPreset": {
         
         
            "set_anchors_preset": "PRESET_FULL_RECT"
         
      
      }  }
   
   ]
     
   }}
  ]
  
  ,
      "styles": [
  
  
  {
     "SizeFlags": {
        
        
           "size_flags_horizontal": "SIZE_EXPAND_FILL",
        
        
           "size_flags_vertical": "SIZE_EXPAND_FILL"
        
     
     }  },
  
  
  {
     "AnchorPreset": {
        
        
           "set_anchors_preset": "PRESET_FULL_RECT"
        
     
     }  }
  
  ]
   
  }},{"HBoxContainer":
  {
     "id": "-49823839919392053355924653945902935680",
     "name": "door Editor Tab 6",
     "children":
  [{"VBoxContainer":
   {
      "id": "158584753966730438625551801410623411878",
      "children":
   [{"Button":
    {
       "id": "-98907141256176298061176575486529314805",
       "text": "Delete Tab",
       "callback": "ViewTabDelete(-49823839919392053355924653945902935680)"
    ,
        "styles": [
    
    
    {
       "FontSize": {
          
          
             "font_size": "20"
          
       
       }  },
    
    
    {
       "Color": {
          
          
             "font_color": "GHOST_WHITE"
          
       
       }  },
    
    
    {
       "StyleBoxFlat": 
          
          
          {
             "normal": {
                
                
                   "bg_color": "INDIAN_RED",
                
                
                   "height": "30",
                
                
                   "width": "50"
                
             
             }  }
       
         }
    
    ]
    
    }},{"Label": {
       "id": "35210184494342396278936992336721178666",
       "text": "Current Machine: 6"
    ,
        "styles": [
    
    
    {
       "FontSize": {
          
          
             "font_size": "20"
          
       
       }  }
    
    ]
    
    }  },{"Label": {
       "id": "122137852452132523495376707294667330797",
       "text": "Select New Machine"
    ,
        "styles": [
    
    
    {
       "FontSize": {
          
          
             "font_size": "20"
          
       
       }  }
    
    ]
    
    }  },{"OptionButton":
    {
       "id": "-17132796761343592319883955172440763769",
       "callback": "ViewTabSetMachine(-49823839919392053355924653945902935680,%machine)"
        ,
       "options":
    ["6"
    ]
     
    ,
        "styles": [
    
    
    {
       "Primitive": {
          
          
             "selected": "Int%0"
          
       
       }  }
    
    ]
     
    }},{"Label": {
       "id": "19531210485360125197504775784234122711",
       "text": "Machine Name"
    ,
        "styles": [
    
    
    {
       "FontSize": {
          
          
             "font_size": "20"
          
       
       }  }
    
    ]
    
    }  },{"TextEdit":
    {
       "id": "148557025074189137737599809947792751906",
       "callback": "MachSetName(6, %text)",
       "text": "door"
    ,
        "styles": [
    
    
    {
       "FontSize": {
          
          
             "font_size": "20"
          
       
       }  },
    
    
    {
       "Vector2": 
          
          
          {
             "custom_minimum_size": {
                
                
                   "x": "200",
                
                
                   "y": "30"
                
             
             }  }
       
         }
    
    ]
    
    }},{"Button":
    {
       "id": "14193630309834683324635255921991820949",
       "text": "Delete Machine",
       "callback": "MachDelete(6)"
    ,
        "styles": [
    
    
    {
       "FontSize": {
          
          
             "font_size": "20"
          
       
       }  },
    
    
    {
       "Color": {
          
          
             "font_color": "GHOST_WHITE"
          
       
       }  },
    
    
    {
       "StyleBoxFlat": 
          
          
          {
             "normal": {
                
                
                   "bg_color": "INDIAN_RED",
                
                
                   "height": "30",
                
                
                   "width": "50"
                
             
             }  }
       
         }
    
    ]
    
    }},{"Button":
    {
       "id": "130098343831597585348298766093900910182",
       "text": "Create State",
       "callback": "StateCreate(11, 6)"
    ,
        "styles": [
    
    
    {
       "FontSize": {
          
          
             "font_size": "20"
          
       
       }  },
    
    
    {
       "Color": {
          
          
             "font_color": "DARK_SLATE_GRAY"
          
       
       }  },
    
    
    {
       "StyleBoxFlat": 
          
          
          {
             "normal": {
                
                
                   "bg_color": "HONEYDEW"
                
             
             }  }
       
         }
    
    ]
    
    }},{"Button":
    {
       "id": "-6065050968004996036798648095876078999",
       "text": "Run Instance of this Machine",
       "callback": "MachInstCreate(11,6)"
    ,
        "styles": [
    
    
    {
       "FontSize": {
          
          
             "font_size": "20"
          
       
       }  },
    
    
    {
       "Color": {
          
          
             "font_color": "DARK_SLATE_GRAY"
          
       
       }  },
    
    
    {
       "StyleBoxFlat": 
          
          
          {
             "normal": {
                
                
                   "bg_color": "HONEYDEW"
                
             
             }  }
       
         }
    
    ]
    
    }},{"OptionButton":
    {
       "id": "63602184905041660192107388622790595219",
       "callback": "ViewTabSetType(-49823839919392053355924653945902935680,%type)"
        ,
       "options":
    ["tree","table"
    ]
     
    ,
        "styles": [
    
    
    {
       "FontSize": {
          
          
             "font_size": "20"
          
       
       }  },
    
    
    {
       "Primitive": {
          
          
             "selected": "Int%1"
          
       
       }  }
    
    ]
     
    }}
   ]
   
   ,
       "styles": [
   
   
   {
      "SizeFlags": {
         
         
            "size_flags_horizontal": "SIZE_EXPAND_FILL",
         
         
            "size_flags_vertical": "SIZE_EXPAND_FILL"
         
      
      }  },
   
   
   {
      "AnchorPreset": {
         
         
            "set_anchors_preset": "PRESET_FULL_RECT"
         
      
      }  }
   
   ]
     
   }},{"VBoxContainer":
   {
      "id": "160075182113990697908883047149578403325",
      "children":
   [{"Label": {
       "id": "-129760349733560546096916230148169225003",
       "text": "Table Representation"
    ,
        "styles": [
    
    
    {
       "FontSize": {
          
          
             "font_size": "30"
          
       
       }  }
    
    ]
    
    }  },{"Label": {
       "id": "-147609087043135124367738880817071223981",
       "text": "Modify States"
    ,
        "styles": [
    
    
    {
       "FontSize": {
          
          
             "font_size": "30"
          
       
       }  }
    
    ]
    
    }  },{"VBoxContainer":
    {
       "id": "-112369514297473951738054025693298787781",
       "children":
    [{"HBoxContainer":
     {
        "id": "-1863724792998409687636159966274309965",
        "children":
     [{"PanelContainer":
      {
         "id": "-27311349313810793913252578568232486435"
       
          ,
         "children":
      [{"Label": {
          "id": "82127735226391364013060338748369925805",
          "text": "Edit State Name"
       
       }  }
      ]
       
      }},{"TextEdit":
      {
         "id": "-83650822923803586469315234967252944264",
         "callback": "StateSetName(7, %text)",
         "text": "opened"
      ,
          "styles": [
      
      
      {
         "FontSize": {
            
            
               "font_size": "20"
            
         
         }  },
      
      
      {
         "Vector2": 
            
            
            {
               "custom_minimum_size": {
                  
                  
                     "x": "200",
                  
                  
                     "y": "30"
                  
               
               }  }
         
           }
      
      ]
      
      }},{"PanelContainer":
      {
         "id": "167934954196332873502204949617076825866"
       
          ,
         "children":
      [{"Button":
       {
          "id": "-128486551712389593481293819024942267987",
          "text": "Delete State",
          "callback": "StateDelete(7)"
       ,
           "styles": [
       
       
       {
          "FontSize": {
             
             
                "font_size": "20"
             
          
          }  },
       
       
       {
          "Color": {
             
             
                "font_color": "GHOST_WHITE"
             
          
          }  },
       
       
       {
          "StyleBoxFlat": 
             
             
             {
                "normal": {
                   
                   
                      "bg_color": "INDIAN_RED",
                   
                   
                      "height": "30",
                   
                   
                      "width": "50"
                   
                
                }  }
          
            }
       
       ]
       
       }}
      ]
       
      }}
     ]
     
     ,
         "styles": [
     
     
     {
        "SizeFlags": {
           
           
              "size_flags_horizontal": "SIZE_EXPAND_FILL",
           
           
              "size_flags_vertical": "SIZE_EXPAND_FILL"
           
        
        }  },
     
     
     {
        "AnchorPreset": {
           
           
              "set_anchors_preset": "PRESET_FULL_RECT"
           
        
        }  }
     
     ]
      
     }},{"HBoxContainer":
     {
        "id": "616071266782260754459701654590976347",
        "children":
     [{"PanelContainer":
      {
         "id": "40557026642821138441878902207614098687"
       
          ,
         "children":
      [{"Label": {
          "id": "-61030487138657927878165183225282544403",
          "text": "Edit State Name"
       
       }  }
      ]
       
      }},{"TextEdit":
      {
         "id": "-53037854474228593029983628337980493082",
         "callback": "StateSetName(8, %text)",
         "text": "closed"
      ,
          "styles": [
      
      
      {
         "FontSize": {
            
            
               "font_size": "20"
            
         
         }  },
      
      
      {
         "Vector2": 
            
            
            {
               "custom_minimum_size": {
                  
                  
                     "x": "200",
                  
                  
                     "y": "30"
                  
               
               }  }
         
           }
      
      ]
      
      }},{"PanelContainer":
      {
         "id": "-147816162918752345566319221257211089951"
       
          ,
         "children":
      [{"Button":
       {
          "id": "169080286518854232128478556401989099760",
          "text": "Delete State",
          "callback": "StateDelete(8)"
       ,
           "styles": [
       
       
       {
          "FontSize": {
             
             
                "font_size": "20"
             
          
          }  },
       
       
       {
          "Color": {
             
             
                "font_color": "GHOST_WHITE"
             
          
          }  },
       
       
       {
          "StyleBoxFlat": 
             
             
             {
                "normal": {
                   
                   
                      "bg_color": "INDIAN_RED",
                   
                   
                      "height": "30",
                   
                   
                      "width": "50"
                   
                
                }  }
          
            }
       
       ]
       
       }}
      ]
       
      }}
     ]
     
     ,
         "styles": [
     
     
     {
        "SizeFlags": {
           
           
              "size_flags_horizontal": "SIZE_EXPAND_FILL",
           
           
              "size_flags_vertical": "SIZE_EXPAND_FILL"
           
        
        }  },
     
     
     {
        "AnchorPreset": {
           
           
              "set_anchors_preset": "PRESET_FULL_RECT"
           
        
        }  }
     
     ]
      
     }}
    ]
    
      
    }},{"Button":
    {
       "id": "-111446964183895149676925532138517636155",
       "text": "Create New State",
       "callback": "StateCreate(11,6)"
    
    }},{"Label": {
       "id": "-65301041352478437650268741873454770958",
       "text": "Transition Table"
    
    }  },{"VBoxContainer":
    {
       "id": "-71478735075468649172159875731598519439",
       "children":
    [{"HBoxContainer":
     {
        "id": "73726074785313871407024660629652628888",
        "children":
     [{"PanelContainer":
      {
         "id": "-169118777344326052017712803290854385885"
      ,
          "styles": [
      
      
      {
         "SizeFlags": {
            
            
               "size_flags_horizontal": "SIZE_EXPAND_FILL",
            
            
               "size_flags_vertical": "SIZE_EXPAND_FILL"
            
         
         }  },
      
      
      {
         "AnchorPreset": {
            
            
               "set_anchors_preset": "PRESET_FULL_RECT"
            
         
         }  },
      
      
      {
         "StyleBoxFlat": 
            
            
            {
               "panel": {
                  
                  
                     "bg_color": "LIGHT_CORAL",
                  
                  
                     "border_width_top": "Long%10",
                  
                  
                     "border_width_bottom": "Long%10",
                  
                  
                     "border_blend": "Bool%true"
                  
               
               }  }
         
           },
      
      
      {
         "FontSize": {
            
            
               "font_size": "20"
            
         
         }  }
      
      ]
       
          ,
         "children":
      [{"Label": {
          "id": "-14900056312113596539336656253788563702",
          "text": "In State"
       
       }  }
      ]
       
      }},{"PanelContainer":
      {
         "id": "90423016363412832151386228401494295172"
      ,
          "styles": [
      
      
      {
         "SizeFlags": {
            
            
               "size_flags_horizontal": "SIZE_EXPAND_FILL",
            
            
               "size_flags_vertical": "SIZE_EXPAND_FILL"
            
         
         }  },
      
      
      {
         "AnchorPreset": {
            
            
               "set_anchors_preset": "PRESET_FULL_RECT"
            
         
         }  },
      
      
      {
         "StyleBoxFlat": 
            
            
            {
               "panel": {
                  
                  
                     "bg_color": "LIGHT_CORAL",
                  
                  
                     "border_width_top": "Long%10",
                  
                  
                     "border_width_bottom": "Long%10",
                  
                  
                     "border_blend": "Bool%true"
                  
               
               }  }
         
           },
      
      
      {
         "FontSize": {
            
            
               "font_size": "20"
            
         
         }  }
      
      ]
       
          ,
         "children":
      [{"Label": {
          "id": "-76050677061943226343500437715288104279",
          "text": "Action"
       
       }  }
      ]
       
      }},{"PanelContainer":
      {
         "id": "-33153657129542131232653767563229710809"
      ,
          "styles": [
      
      
      {
         "SizeFlags": {
            
            
               "size_flags_horizontal": "SIZE_EXPAND_FILL",
            
            
               "size_flags_vertical": "SIZE_EXPAND_FILL"
            
         
         }  },
      
      
      {
         "AnchorPreset": {
            
            
               "set_anchors_preset": "PRESET_FULL_RECT"
            
         
         }  },
      
      
      {
         "StyleBoxFlat": 
            
            
            {
               "panel": {
                  
                  
                     "bg_color": "LIGHT_CORAL",
                  
                  
                     "border_width_top": "Long%10",
                  
                  
                     "border_width_bottom": "Long%10",
                  
                  
                     "border_blend": "Bool%true"
                  
               
               }  }
         
           },
      
      
      {
         "FontSize": {
            
            
               "font_size": "20"
            
         
         }  }
      
      ]
       
          ,
         "children":
      [{"Label": {
          "id": "-97416793830673721279523295381754473414",
          "text": "Out State"
       
       }  }
      ]
       
      }},{"PanelContainer":
      {
         "id": "-160320323465499839437778521748177687443"
      ,
          "styles": [
      
      
      {
         "SizeFlags": {
            
            
               "size_flags_horizontal": "SIZE_EXPAND_FILL",
            
            
               "size_flags_vertical": "SIZE_EXPAND_FILL"
            
         
         }  },
      
      
      {
         "AnchorPreset": {
            
            
               "set_anchors_preset": "PRESET_FULL_RECT"
            
         
         }  },
      
      
      {
         "StyleBoxFlat": 
            
            
            {
               "panel": {
                  
                  
                     "bg_color": "LIGHT_CORAL",
                  
                  
                     "border_width_top": "Long%10",
                  
                  
                     "border_width_bottom": "Long%10",
                  
                  
                     "border_blend": "Bool%true"
                  
               
               }  }
         
           },
      
      
      {
         "FontSize": {
            
            
               "font_size": "20"
            
         
         }  }
      
      ]
       
          ,
         "children":
      [{"Label": {
          "id": "-63046708604130301141993996667110288252",
          "text": ""
       
       }  }
      ]
       
      }}
     ]
     
     ,
         "styles": [
     
     
     {
        "SizeFlags": {
           
           
              "size_flags_horizontal": "SIZE_EXPAND_FILL",
           
           
              "size_flags_vertical": "SIZE_EXPAND_FILL"
           
        
        }  },
     
     
     {
        "AnchorPreset": {
           
           
              "set_anchors_preset": "PRESET_FULL_RECT"
           
        
        }  }
     
     ]
      
     }}
    ]
    
      
    }},{"VBoxContainer":
    {
       "id": "52023288264963535131403961223961388994",
       "children":
    [{"HBoxContainer":
     {
        "id": "-737200873669692606964869706923082425",
        "children":
     [{"PanelContainer":
      {
         "id": "59642098706677058785203451047735163498"
       
          ,
         "children":
      [{"OptionButton":
       {
          "id": "55188686929575179269399910337853957013",
          "callback": "InterTransSetTarget(9,%state)"
           ,
          "options":
       ["opened","closed"
       ]
        
       ,
           "styles": [
       
       
       {
          "FontSize": {
             
             
                "font_size": "20"
             
          
          }  },
       
       
       {
          "Primitive": {
             
             
                "selected": "Int%0",
             
             
                "allow_reselect": "Boolean%true"
             
          
          }  }
       
       ]
        
       }}
      ]
       
      }},{"PanelContainer":
      {
         "id": "-154680570717042035503369241189894511317"
       
          ,
         "children":
      [{"TextEdit":
       {
          "id": "29106822476866058465485173010789954902",
          "callback": "TransSetTrigger(9, %text)",
          "text": "close"
       ,
           "styles": [
       
       
       {
          "FontSize": {
             
             
                "font_size": "20"
             
          
          }  },
       
       
       {
          "Vector2": 
             
             
             {
                "custom_minimum_size": {
                   
                   
                      "x": "200",
                   
                   
                      "y": "30"
                   
                
                }  }
          
            }
       
       ]
       
       }}
      ]
       
      }},{"PanelContainer":
      {
         "id": "-75770576035627008389164049424538342364"
       
          ,
         "children":
      [{"OptionButton":
       {
          "id": "-25995409008867780898448895295363583981",
          "callback": "InterTransSetTarget(9,%state)"
           ,
          "options":
       ["opened","closed"
       ]
        
       ,
           "styles": [
       
       
       {
          "FontSize": {
             
             
                "font_size": "20"
             
          
          }  },
       
       
       {
          "Primitive": {
             
             
                "selected": "Int%1",
             
             
                "allow_reselect": "Boolean%true"
             
          
          }  }
       
       ]
        
       }}
      ]
       
      }},{"PanelContainer":
      {
         "id": "46701031668281296731581274188544771921"
       
          ,
         "children":
      [{"Button":
       {
          "id": "-25797125951477449828848725708113703830",
          "text": "Delete Transition",
          "callback": "TransDelete(9)"
       ,
           "styles": [
       
       
       {
          "FontSize": {
             
             
                "font_size": "20"
             
          
          }  },
       
       
       {
          "Color": {
             
             
                "font_color": "GHOST_WHITE"
             
          
          }  },
       
       
       {
          "StyleBoxFlat": 
             
             
             {
                "normal": {
                   
                   
                      "bg_color": "INDIAN_RED",
                   
                   
                      "height": "30",
                   
                   
                      "width": "50"
                   
                
                }  }
          
            }
       
       ]
       
       }}
      ]
       
      }}
     ]
     
     ,
         "styles": [
     
     
     {
        "SizeFlags": {
           
           
              "size_flags_horizontal": "SIZE_EXPAND_FILL",
           
           
              "size_flags_vertical": "SIZE_EXPAND_FILL"
           
        
        }  },
     
     
     {
        "AnchorPreset": {
           
           
              "set_anchors_preset": "PRESET_FULL_RECT"
           
        
        }  }
     
     ]
      
     }},{"HBoxContainer":
     {
        "id": "-25054911759400210660034656124625025017",
        "children":
     [{"PanelContainer":
      {
         "id": "-92902872105527380502670737849264027096"
       
          ,
         "children":
      [{"OptionButton":
       {
          "id": "168005380458451421254280768245116991197",
          "callback": "InterTransSetTarget(10,%state)"
           ,
          "options":
       ["opened","closed"
       ]
        
       ,
           "styles": [
       
       
       {
          "FontSize": {
             
             
                "font_size": "20"
             
          
          }  },
       
       
       {
          "Primitive": {
             
             
                "selected": "Int%1",
             
             
                "allow_reselect": "Boolean%true"
             
          
          }  }
       
       ]
        
       }}
      ]
       
      }},{"PanelContainer":
      {
         "id": "132899716972262722622266775260498659645"
       
          ,
         "children":
      [{"TextEdit":
       {
          "id": "-114938671548887165144286277711539910626",
          "callback": "TransSetTrigger(10, %text)",
          "text": "open"
       ,
           "styles": [
       
       
       {
          "FontSize": {
             
             
                "font_size": "20"
             
          
          }  },
       
       
       {
          "Vector2": 
             
             
             {
                "custom_minimum_size": {
                   
                   
                      "x": "200",
                   
                   
                      "y": "30"
                   
                
                }  }
          
            }
       
       ]
       
       }}
      ]
       
      }},{"PanelContainer":
      {
         "id": "160775682880013966817084779454718736508"
       
          ,
         "children":
      [{"OptionButton":
       {
          "id": "14808119476394358196880324082881184625",
          "callback": "InterTransSetTarget(10,%state)"
           ,
          "options":
       ["opened","closed"
       ]
        
       ,
           "styles": [
       
       
       {
          "FontSize": {
             
             
                "font_size": "20"
             
          
          }  },
       
       
       {
          "Primitive": {
             
             
                "selected": "Int%0",
             
             
                "allow_reselect": "Boolean%true"
             
          
          }  }
       
       ]
        
       }}
      ]
       
      }},{"PanelContainer":
      {
         "id": "143880164585214653912574301878551506627"
       
          ,
         "children":
      [{"Button":
       {
          "id": "-57167849905383553241578207653019403195",
          "text": "Delete Transition",
          "callback": "TransDelete(10)"
       ,
           "styles": [
       
       
       {
          "FontSize": {
             
             
                "font_size": "20"
             
          
          }  },
       
       
       {
          "Color": {
             
             
                "font_color": "GHOST_WHITE"
             
          
          }  },
       
       
       {
          "StyleBoxFlat": 
             
             
             {
                "normal": {
                   
                   
                      "bg_color": "INDIAN_RED",
                   
                   
                      "height": "30",
                   
                   
                      "width": "50"
                   
                
                }  }
          
            }
       
       ]
       
       }}
      ]
       
      }}
     ]
     
     ,
         "styles": [
     
     
     {
        "SizeFlags": {
           
           
              "size_flags_horizontal": "SIZE_EXPAND_FILL",
           
           
              "size_flags_vertical": "SIZE_EXPAND_FILL"
           
        
        }  },
     
     
     {
        "AnchorPreset": {
           
           
              "set_anchors_preset": "PRESET_FULL_RECT"
           
        
        }  }
     
     ]
      
     }},{"Button":
     {
        "id": "-11091520675629398239211843973480150956",
        "text": "Create new Transition",
        "callback": ""
     
     }}
    ]
    
      
    }}
   ]
   
   ,
       "styles": [
   
   
   {
      "SizeFlags": {
         
         
            "size_flags_horizontal": "SIZE_EXPAND_FILL",
         
         
            "size_flags_vertical": "SIZE_EXPAND_FILL"
         
      
      }  },
   
   
   {
      "AnchorPreset": {
         
         
            "set_anchors_preset": "PRESET_FULL_RECT"
         
      
      }  }
   
   ]
     
   }}
  ]
  
  ,
      "styles": [
  
  
  {
     "SizeFlags": {
        
        
           "size_flags_horizontal": "SIZE_EXPAND_FILL",
        
        
           "size_flags_vertical": "SIZE_EXPAND_FILL"
        
     
     }  },
  
  
  {
     "AnchorPreset": {
        
        
           "set_anchors_preset": "PRESET_FULL_RECT"
        
     
     }  }
  
  ]
   
  }}
 ]
  
 }}
]
}